GeoValidator
