Metadata-Version: 1.2
Name: Geo-Validator
Version: 1.1.5
Summary: Validates Lat/Long coords with address
Home-page: https://github.com/Cheff789/GeoValidator
Author: R. P. H.
Author-email: rhaynes09@yahoo.com
License: MIT
Keywords: latitude longitude address
Platform: UNKNOWN
Classifier: Development Status :: 3 - Alpha
Classifier: Intended Audience :: Developers
Classifier: Topic :: Software Development :: Build Tools
Classifier: License :: OSI Approved :: MIT License
Classifier: Programming Language :: Python :: 3
Classifier: Programming Language :: Python :: 3.3
Classifier: Programming Language :: Python :: 3.4
Classifier: Programming Language :: Python :: 3.5
Requires-Python: >=3
